{
  "pr_number": 180839,
  "pr_url": "https://github.com/llvm/llvm-project/pull/180839",
  "title": "InstCombine: Fix wrong insert point for fdiv->copysign simplify",
  "commit_sha": "3772275ace0f30d238bc3903a84a1a472732cc25",
  "components": [
    "InstCombine"
  ],
  "lit_test_dir": [
    "llvm/test/Transforms/InstCombine"
  ],
  "hints": {
    "components": [
      "InstCombine"
    ],
    "bug_location_lineno": {
      "llvm/lib/Transforms/InstCombine/InstCombineSimplifyDemanded.cpp": [
        [
          2711,
          2716
        ],
        [
          2726,
          2731
        ]
      ]
    },
    "bug_location_funcname": {
      "llvm/lib/Transforms/InstCombine/InstCombineSimplifyDemanded.cpp": [
        "InstCombinerImpl::SimplifyDemandedUseFPClass"
      ]
    }
  },
  "source_patch": "diff --git a/llvm/lib/Transforms/InstCombine/InstCombineSimplifyDemanded.cpp b/llvm/lib/Transforms/InstCombine/InstCombineSimplifyDemanded.cpp\nindex ee66ccc3f7149..98f7131cdcb4e 100644\n--- a/llvm/lib/Transforms/InstCombine/InstCombineSimplifyDemanded.cpp\n+++ b/llvm/lib/Transforms/InstCombine/InstCombineSimplifyDemanded.cpp\n@@ -2711,6 +2711,9 @@ Value *InstCombinerImpl::SimplifyDemandedUseFPClass(Instruction *I,\n       return ConstantFP::getZero(VTy);\n \n     if (KnownLHS.isKnownAlways(fcPosZero) && KnownRHS.isKnownNeverNaN()) {\n+      IRBuilderBase::InsertPointGuard Guard(Builder);\n+      Builder.SetInsertPoint(I);\n+\n       // nnan +0 / x -> copysign(0, rhs)\n       // TODO: -0 / x => copysign(0, fneg(rhs))\n       Value *Copysign = Builder.CreateCopySign(X, Y, FMF);\n@@ -2726,6 +2729,9 @@ Value *InstCombinerImpl::SimplifyDemandedUseFPClass(Instruction *I,\n                            KnownLHS.isKnownNeverLogicalZero(Mode))) &&\n          (KnownRHS.isKnownAlways(fcPosZero) ||\n           (FMF.noSignedZeros() && KnownRHS.isKnownAlways(fcZero))))) {\n+      IRBuilderBase::InsertPointGuard Guard(Builder);\n+      Builder.SetInsertPoint(I);\n+\n       // nnan x / 0 => copysign(inf, x);\n       // nnan nsz x / -0 => copysign(inf, x);\n       Value *Copysign =\n",
  "test_patch": "diff --git a/llvm/test/Transforms/InstCombine/simplify-demanded-fpclass-fdiv.ll b/llvm/test/Transforms/InstCombine/simplify-demanded-fpclass-fdiv.ll\nindex 9132ca2b6f572..bdde6b3a72dad 100644\n--- a/llvm/test/Transforms/InstCombine/simplify-demanded-fpclass-fdiv.ll\n+++ b/llvm/test/Transforms/InstCombine/simplify-demanded-fpclass-fdiv.ll\n@@ -826,6 +826,18 @@ define nofpclass(nan) half @ret_no_nan_result__known_pzero__fdiv__not_inf(half n\n   ret half %div\n }\n \n+define nofpclass(nan) half @ret_no_nan_result__known_pzero__fdiv__not_inf__insert_point(half nofpclass(inf sub norm nzero) %pzero.or.nan, half nofpclass(inf nan) %not.inf.or.nan) {\n+; CHECK-LABEL: define nofpclass(nan) half @ret_no_nan_result__known_pzero__fdiv__not_inf__insert_point(\n+; CHECK-SAME: half nofpclass(inf nzero sub norm) [[PZERO_OR_NAN:%.*]], half nofpclass(nan inf) [[NOT_INF_OR_NAN:%.*]]) {\n+; CHECK-NEXT:    [[DIV:%.*]] = call half @llvm.copysign.f16(half 0xH0000, half [[NOT_INF_OR_NAN]])\n+; CHECK-NEXT:    [[BARRIER:%.*]] = call half @llvm.arithmetic.fence.f16(half [[DIV]])\n+; CHECK-NEXT:    ret half [[BARRIER]]\n+;\n+  %div = fdiv half %pzero.or.nan, %not.inf.or.nan\n+  %barrier = call half @llvm.arithmetic.fence.f16(half %div)\n+  ret half %barrier\n+}\n+\n ; Should be able to fold to copysign, helped by the lack of nan results.\n define nofpclass(nan) half @ret_no_nan_result__not_inf_or_nan__fdiv__known_pzero_or_nan(half nofpclass(inf) %not.inf.or.nan, half nofpclass(inf sub norm nzero) %pzero.or.nan) {\n ; CHECK-LABEL: define nofpclass(nan) half @ret_no_nan_result__not_inf_or_nan__fdiv__known_pzero_or_nan(\n@@ -837,6 +849,18 @@ define nofpclass(nan) half @ret_no_nan_result__not_inf_or_nan__fdiv__known_pzero\n   ret half %div\n }\n \n+define nofpclass(nan) half @ret_no_nan_result__not_inf_or_nan__fdiv__known_pzero_or_nan__insert_pt(half nofpclass(inf) %not.inf.or.nan, half nofpclass(inf sub norm nzero) %pzero.or.nan) {\n+; CHECK-LABEL: define nofpclass(nan) half @ret_no_nan_result__not_inf_or_nan__fdiv__known_pzero_or_nan__insert_pt(\n+; CHECK-SAME: half nofpclass(inf) [[NOT_INF_OR_NAN:%.*]], half nofpclass(inf nzero sub norm) [[PZERO_OR_NAN:%.*]]) {\n+; CHECK-NEXT:    [[DIV:%.*]] = call half @llvm.copysign.f16(half 0xH7C00, half [[NOT_INF_OR_NAN]])\n+; CHECK-NEXT:    [[BARRIER:%.*]] = call half @llvm.arithmetic.fence.f16(half [[DIV]])\n+; CHECK-NEXT:    ret half [[BARRIER]]\n+;\n+  %div = fdiv half %not.inf.or.nan, %pzero.or.nan\n+  %barrier = call half @llvm.arithmetic.fence.f16(half %div)\n+  ret half %barrier\n+}\n+\n ; -> fneg, with help of no nan results\n define nofpclass(nan) half @ret_no_nan_result__known_inf_or_nan__fdiv__known_negative_non0(half nofpclass(zero sub norm) %inf.or.nan, half nofpclass(zero pinf pnorm psub) %negative.non0) {\n ; CHECK-LABEL: define nofpclass(nan) half @ret_no_nan_result__known_inf_or_nan__fdiv__known_negative_non0(\n",
  "source_files": [
    "llvm/lib/Transforms/InstCombine/InstCombineSimplifyDemanded.cpp"
  ],
  "test_files": [
    "llvm/test/Transforms/InstCombine/simplify-demanded-fpclass-fdiv.ll"
  ],
  "tests": [],
  "has_test_changes": false,
  "has_source_changes": true,
  "properties": {
    "is_single_file_fix": true,
    "is_single_func_fix": true
  }
}