{
  "pr_number": 107314,
  "title": "[InstCombine] Fold `(x == y) ? 0 : (x > y ? 1 : -1)` into `ucmp/scmp(x,y)`",
  "before_test_name": "test_high_ne",
  "num_after_cases": 29,
  "summary": "The developers generalized a specific pattern for converting a three-way comparison (spaceship operator) into an intrinsic by identifying the core structure: `(x == y) ? 0 : ((x > y) ? 1 : -1)`. They extended the transformation to handle:\n\n1. **Multiple predicate variations**: Not just `ne` but also `sle`, `slt`, `sge`, `sgt` comparisons against the result.\n2. **Commutations**: Swapped operands and inverted select conditions (e.g., `(x < y) ? -1 : 1` instead of `(x > y) ? 1 : -1`).\n3. **Both signed and unsigned comparisons**: Supporting `scmp` and `ucmp` intrinsics.\n4. **Edge cases**: Ensuring constants are exactly `1` and `-1`, and rejecting mismatched predicates or constants.\n\nThe patch adds logic to detect the generalized pattern by matching the select-of-constants structure, validating the constants, and determining signedness from the inner comparison predicate. This turns a family of manual comparisons into a single intrinsic call, simplifying codegen across architectures.\n\n**Key insight**: The transformation works by recognizing that any comparison of the three-way result against `{-1,0,1}` can be folded into the intrinsic, as the intrinsic directly produces that ternary result."
}