{
  "pr_number": 69581,
  "title": "[InstCombine] Canonicalise SextADD + GEP",
  "before_test_name": "test",
  "num_after_cases": 3,
  "summary": "The developers generalized an InstCombine transformation by expanding a pattern match from a simple constant addition to handle variable operands and different usage contexts. Originally, the optimization only recognized `add nsw i32 %a, 10` followed by sext and GEP. The generalized version adds a new matcher that captures `add nsw` with any constant, not just a specific one, and ensures the sext and GEP uses are compatible.\n\nKey generalization steps:\n1. **Pattern flexibility**: Changed from matching a fixed constant (`10`) to matching any `ConstantInt` (`C`), allowing transformations like `add nsw i32 %a, 5`.\n2. **Usage validation**: Added checks for `OneUse` on critical operations to ensure safety when rewriting the IR.\n3. **Flag awareness**: The pattern now explicitly requires `nsw` (no signed wrap) to preserve overflow semantics, preventing incorrect transformations for plain `add`.\n4. **Operand generalization**: The transformation handles both the original case and new test cases where the second operand isn't constant (`test_add_op2_not_constant`) or the result has multiple uses (`test_add_res_moreoneuse`).\n\nThe strategy demonstrates how to evolve a specific optimization into a robust, general-purpose transformation by identifying the core constraints (one-use chains, overflow flags) and making the pattern matching more flexible while maintaining safety."
}