{
  "pr_number": 79717,
  "title": "[InstCombine] Add (A & B) - (A & ~B) --> B - (A ^ B)",
  "before_test_name": "sub_and_xor",
  "num_after_cases": 2,
  "summary": "The developers generalized the pattern by recognizing the underlying algebraic identity `(A & ~B) - (A & B) = (A ^ B) - B` (and its symmetric counterpart). They extended the transformation to handle both operand orderings and added support for commutative matching (`m_c_And`) to capture variations like `and i32 %B, %A` vs `and i32 %A, %B`. The patch also preserves the original instruction's `nsw`/`nuw` flags, ensuring no loss of optimization potential.\n\nKey takeaways for similar generalizations:\n1. **Identify core algebraic equivalence** behind a specific case.\n2. **Use commutative matchers** (`m_c_*`) to cover operand order variations.\n3. **Handle symmetric patterns** explicitly (both `Op0`/`Op1` orderings).\n4. **Preserve instruction flags** (like wrapping flags) when creating replacements.\n5. **Test with varied forms** (as shown in `sub_xor_and`) to validate robustness.\n\nThis approach transforms a single-case optimization into a reusable, order-agnostic transformation."
}