{
  "pr_number": 89701,
  "title": "[InstCombine] Fix poison propagation in select of bitwise fold",
  "before_test_name": "src_and_eq_C_xor_OrAndNotC_vec_poison",
  "num_after_cases": 0,
  "summary": "The developers generalized the pattern by enhancing pattern matching to handle poison elements selectively. The original test case required matching `not` operations (`xor %val, -1`) where poison elements in the constant must be ignored for correctness. The patch introduces a new matcher `m_NotForbidPoison()` that uses `m_AllOnesForbidPoison()` to ensure poison elements are **not** ignored during matching, preventing incorrect transformations when poison is present in the vector constant.\n\nKey changes:\n1. Extended `cstval_pred_ty` with a template parameter `AllowPoison` to control poison handling.\n2. Added `m_AllOnesForbidPoison()` and `m_NotForbidPoison()` for strict matching.\n3. Updated `foldSelectICmpEq` to use the stricter matcher when folding `select` with `icmp eq` and `not` patterns.\n\nThis approach allows the optimization to safely apply to vectors with poison while maintaining correctness. Developers can reuse this strategy by parameterizing existing matchers to control poison sensitivity, ensuring optimizations are both general and safe."
}