{
  "pr_number": 91089,
  "title": "release/18.x: [InstCombine] Fix miscompile in negation of select (#89698)",
  "before_test_name": "dont_negate_ordinary_select",
  "num_after_cases": 2,
  "summary": "The developers generalized the pattern by enhancing `isKnownNegation()` to handle poison-safe detection and extending its use in `InstCombineNegator`. Initially, the optimization only recognized `sub(z, select(c, x, y))` when `x` and `y` were direct negations. The patch adds an `AllowPoison` parameter to ignore non-zero constants (like `poison`), ensuring safety for `freeze` and select with poison operands. This allows the function to identify negation pairs in broader contexts, such as `freeze(sub(x, y))` or `select(c, neg, x)` where `neg` may contain poison. The negator then uses this improved check to swap select arms safely, enabling transformations like converting `sub(0, select(c, -x, x))` into `select(c, x, -x)`. The key insight is to decouple negation detection from specific IR patterns, making it reusable across instructions like `select` and `freeze` while preserving poison semantics."
}